{"selector":".social-link","queries":[{"elements":[{"selector":".social-link","values":{"border":"calc(0.2rh + 0.2rw) solid #999","borderRadius":"calc(0.3rh + 0.3rw)","fontSize":"85rmin"}}]},{"conditions":[[["aspect-ratio",">",3]]],"elements":[{"selector":".social-link","values":{"fontSize":"60rh"}}]},{"conditions":[[["aspect-ratio",">",3]]],"elements":[{"selector":".social-link__icon","values":{"marginLeft":"20rh"}}]},{"conditions":[[["aspect-ratio",">",3]]],"elements":[{"selector":".social-link__name","styles":{"display":"block"},"values":{"marginLeft":"5rw","marginRight":"20rh"}}]}]}